ai_catalyst/__init__.py
ai_catalyst/config/__init__.py
ai_catalyst/config/manager.py
ai_catalyst/data/__init__.py
ai_catalyst/data/pii/__init__.py
ai_catalyst/data/pii/processor.py
ai_catalyst/data/processors/__init__.py
ai_catalyst/data/processors/file_processor.py
ai_catalyst/database/__init__.py
ai_catalyst/database/manager.py
ai_catalyst/llm/__init__.py
ai_catalyst/llm/provider.py
ai_catalyst/monitoring/__init__.py
ai_catalyst/monitoring/system_monitor.py
ai_catalyst/resilience/__init__.py
ai_catalyst/resilience/circuit_breaker.py
ai_catalyst/resilience/health_checker.py
ai_catalyst/resilience/retry_handler.py
ai_catalyst/security/__init__.py
ai_catalyst/security/audit_logger.py
ai_catalyst/security/config_vault.py
ai_catalyst/security/key_vault.py
ai_catalyst/security/rate_limiter.py
ai_catalyst-0.1.1.dist-info/licenses/LICENSE
ai_catalyst-0.1.1.dist-info/METADATA
ai_catalyst-0.1.1.dist-info/WHEEL
ai_catalyst-0.1.1.dist-info/top_level.txt
ai_catalyst-0.1.1.dist-info/RECORD
