Metadata-Version: 2.4
Name: ai-catalyst
Version: 0.1.1
Summary: Production-ready AI components framework with security and resilience
Author-email: Eric Medlock <your.email@example.com>
License: MIT
Project-URL: Homepage, https://github.com/ericmedlock/AI_Catalyst
Project-URL: Repository, https://github.com/ericmedlock/AI_Catalyst
Project-URL: Documentation, https://github.com/ericmedlock/AI_Catalyst#readme
Project-URL: Bug Tracker, https://github.com/ericmedlock/AI_Catalyst/issues
Keywords: ai,llm,security,async,pii,resilience
Classifier: Development Status :: 4 - Beta
Classifier: Intended Audience :: Developers
Classifier: License :: OSI Approved :: MIT License
Classifier: Operating System :: OS Independent
Classifier: Programming Language :: Python :: 3
Classifier: Programming Language :: Python :: 3.9
Classifier: Programming Language :: Python :: 3.10
Classifier: Programming Language :: Python :: 3.11
Classifier: Programming Language :: Python :: 3.12
Classifier: Topic :: Software Development :: Libraries :: Python Modules
Classifier: Topic :: Scientific/Engineering :: Artificial Intelligence
Requires-Python: >=3.9
License-File: LICENSE
Requires-Dist: asyncpg>=0.28.0
Requires-Dist: aiohttp>=3.8.0
Requires-Dist: aiofiles>=23.0.0
Requires-Dist: pyyaml>=6.0
Requires-Dist: psutil>=5.9.0
Requires-Dist: openai>=1.0.0
Requires-Dist: regex>=2023.0.0
Requires-Dist: pandas>=2.0.0
Requires-Dist: cryptography>=41.0.0
Provides-Extra: dev
Requires-Dist: pytest>=7.0.0; extra == "dev"
Requires-Dist: pytest-asyncio>=0.21.0; extra == "dev"
Requires-Dist: black>=23.0.0; extra == "dev"
Requires-Dist: flake8>=6.0.0; extra == "dev"
Requires-Dist: mypy>=1.0.0; extra == "dev"
Provides-Extra: test
Requires-Dist: pytest>=7.0.0; extra == "test"
Requires-Dist: pytest-asyncio>=0.21.0; extra == "test"
Dynamic: license-file
